MANIFEST.in
release_to_pypi.bat
setup.cfg
setup.py
PyBus.egg-info/PKG-INFO
PyBus.egg-info/SOURCES.txt
PyBus.egg-info/dependency_links.txt
PyBus.egg-info/entry_points.txt
PyBus.egg-info/top_level.txt
PyBus.egg-info/zip-safe
pybus/__init__.py
pybus/pybus_core.py
tests/py_bus_test_base.py
tests/test_message_bus.py