Metadata-Version: 1.0
Name: PyBus
Version: 0.1dev-r920
Summary: PyBus is a message bus
Home-page: http://www.pybus.org
Author: Bernardo Heynemann
Author-email: heynemann@gmail.com
License: OSI
Keywords: message bus
Platform: UNKNOWN
